{
    "packageId": 1670,
    "type": "GHROW",
    "name": "The Ghan Expedition Darwin to Adelaide with Charles Darwin Sunset Dinner Cruise",
    "code": "DHCBRTAPTEX7",
    "description": "Lap up one of Darwin's spectacular sunsets over dinner on board Darwin Harbour Cruises. The next morning, be transferred from your accommodation (as booked by you) to join your four-day three-night Ghan Expedition rail journey that will take you into the nation's heart. In addition to exploring Katherine on your first day of this all-inclusive adventure, there is a full day of touring Alice Springs that concludes with dinner under the stars, plus another full day exploring the truly unique underground mining town of Coober Pedy. Wake-up on your final day to a view of the Flinders Ranges outside your window before arriving in Adelaide.\r\nPlease Note: Accommodation is not included",
    "duration": 5,
    "alternatePackageCode": "",
    "bookingTypeId": 2,
    "priceTypeId": 3,
    "isRecommendedProduct": false,
    "packageImageUrl": "https://jbre-obe-frontend-test.azurewebsites.net/assets/images/package/GHROW-DHCBRTAPTEX.jpg",
    "alternativePackageImageUrl": "https://jbre-obe-frontend-test.azurewebsites.net/assets/images/package/noimg.jpg",
    "departures": [
        {
            "departureId": 142553,
            "startDate": "2024-05-14T09:00:00",
            "startRegion": "Darwin",
            "endDate": "2024-05-18T11:50:00",
            "endRegion": "Adelaide",
            "hasCabinPriceTypes": true,
            "bookingKey": "The Ghan Expedition Darwin to Adelaide with Charles Darwin Sunset Dinner Cruise 14 May 2024",
            "cabins": [
                {
                    "elementId": 27631,
                    "name": "Gold Premium Suite Cabin",
                    "elementIdSole": 27632,
                    "soleOccupancyName": "Gold Premium Suite Cabin",
                    "serviceLevel": 6,
                    "serviceType": "Gold Premium Suite",
                    "occupancyId": 3,
                    "roomsLeft": 0,
                    "totalWaitlistAvailable": 0,
                    "startingPrice": 7670.0,
                    "startingSolePrice": 13700.0,
                    "priceTypes": []
                },
                {
                    "elementId": 23997,
                    "name": "Gold Premium Twin Cabin",
                    "elementIdSole": 23998,
                    "soleOccupancyName": "Gold Premium Twin Cabin",
                    "serviceLevel": 6,
                    "serviceType": "Gold Premium Twin",
                    "occupancyId": 3,
                    "roomsLeft": 1,
                    "totalWaitlistAvailable": 0,
                    "startingPrice": 5865.0,
                    "startingSolePrice": 10420.0,
                    "priceTypes": [
                        {
                            "priceTypeId": 16,
                            "priceTypeName": "Saver",
                            "adultPrice": 5865.0,
                            "soleAdultPrice": 10420.0,
                            "childPrice": 4692.0,
                            "isConcessionFare": false,
                            "terms": "This fare is a discounted fare and is subject to availability. 25% cancellation fees apply when cancelling more than 45 days prior to departure. 100% cancellation fees apply 45 days and under prior to departure.",
                            "isClassicReward": false,
                            "burnRate": 0.0055600000,
                            "earnRate": 1.0000000000,
                            "isWaitListPriceType": false
                        },
                        {
                            "priceTypeId": 2,
                            "priceTypeName": "Everyday",
                            "adultPrice": 6170.0,
                            "soleAdultPrice": 10970.0,
                            "childPrice": 4936.0,
                            "isConcessionFare": false,
                            "terms": "A 25% deposit is due upon booking. Final payment is due 45 days prior to departure. Cancelling more than 45 days prior to departure will result a loss in deposit. 100% cancellation fees apply if cancelled 45 days or less than departure.",
                            "isClassicReward": false,
                            "burnRate": 0.0055600000,
                            "earnRate": 1.0000000000,
                            "isWaitListPriceType": false
                        },
                        {
                            "priceTypeId": 610,
                            "priceTypeName": "Flexible",
                            "adultPrice": 6750.0,
                            "soleAdultPrice": 12050.0,
                            "childPrice": 5400.0,
                            "isConcessionFare": false,
                            "terms": "Changes are permitted up to 1 day prior to departure. Fully refundable up until 1 day prior to departure.",
                            "isClassicReward": false,
                            "burnRate": 0.0055600000,
                            "earnRate": 1.0000000000,
                            "isWaitListPriceType": false
                        }
                    ]
                },
                {
                    "elementId": 23985,
                    "name": "Gold Single Cabin",
                    "elementIdSole": 23985,
                    "soleOccupancyName": "Gold Single Cabin",
                    "serviceLevel": 3,
                    "serviceType": "Gold Single",
                    "occupancyId": 1,
                    "roomsLeft": 3,
                    "totalWaitlistAvailable": 0,
                    "startingPrice": 4100.0,
                    "startingSolePrice": 4100.0,
                    "priceTypes": [
                        {
                            "priceTypeId": 3,
                            "priceTypeName": "Advance Purchase",
                            "adultPrice": 4100.0,
                            "soleAdultPrice": 4100.0,
                            "childPrice": 0,
                            "isConcessionFare": false,
                            "terms": "This fare is a discounted fare available for bookings made 6 months in advance and is subject to availability. 100% cancellation fees apply 14 days after booking date.",
                            "isClassicReward": false,
                            "burnRate": 0.0055600000,
                            "earnRate": 1.0000000000,
                            "isWaitListPriceType": false
                        },
                        {
                            "priceTypeId": 16,
                            "priceTypeName": "Saver",
                            "adultPrice": 4320.0,
                            "soleAdultPrice": 4320.0,
                            "childPrice": 0,
                            "isConcessionFare": false,
                            "terms": "This fare is a discounted fare and is subject to availability. 25% cancellation fees apply when cancelling more than 45 days prior to departure. 100% cancellation fees apply 45 days and under prior to departure.",
                            "isClassicReward": false,
                            "burnRate": 0.0055600000,
                            "earnRate": 1.0000000000,
                            "isWaitListPriceType": false
                        },
                        {
                            "priceTypeId": 2,
                            "priceTypeName": "Everyday",
                            "adultPrice": 4545.0,
                            "soleAdultPrice": 4545.0,
                            "childPrice": 0,
                            "isConcessionFare": false,
                            "terms": "A 25% deposit is due upon booking. Final payment is due 45 days prior to departure. Cancelling more than 45 days prior to departure will result a loss in deposit. 100% cancellation fees apply if cancelled 45 days or less than departure.",
                            "isClassicReward": false,
                            "burnRate": 0.0055600000,
                            "earnRate": 1.0000000000,
                            "isWaitListPriceType": false
                        },
                        {
                            "priceTypeId": 610,
                            "priceTypeName": "Flexible",
                            "adultPrice": 4985.0,
                            "soleAdultPrice": 4985.0,
                            "childPrice": 0,
                            "isConcessionFare": false,
                            "terms": "Changes are permitted up to 1 day prior to departure. Fully refundable up until 1 day prior to departure.",
                            "isClassicReward": false,
                            "burnRate": 0.0055600000,
                            "earnRate": 1.0000000000,
                            "isWaitListPriceType": false
                        }
                    ]
                },
                {
                    "elementId": 23987,
                    "name": "Gold Suite Cabin",
                    "elementIdSole": 23988,
                    "soleOccupancyName": "Gold Suite Cabin",
                    "serviceLevel": 2,
                    "serviceType": "Gold Suite",
                    "occupancyId": 3,
                    "roomsLeft": 0,
                    "totalWaitlistAvailable": 0,
                    "startingPrice": 6980.0,
                    "startingSolePrice": 12455.0,
                    "priceTypes": []
                },
                {
                    "elementId": 23989,
                    "name": "Gold Twin Cabin",
                    "elementIdSole": 23990,
                    "soleOccupancyName": "Gold Twin Cabin",
                    "serviceLevel": 2,
                    "serviceType": "Gold Twin",
                    "occupancyId": 3,
                    "roomsLeft": 0,
                    "totalWaitlistAvailable": 0,
                    "startingPrice": 4650.0,
                    "startingSolePrice": 8260.0,
                    "priceTypes": []
                },
                {
                    "elementId": 23993,
                    "name": "Platinum Double Cabin",
                    "elementIdSole": 23994,
                    "soleOccupancyName": "Platinum Double Cabin",
                    "serviceLevel": 1,
                    "serviceType": "Platinum Double",
                    "occupancyId": 3,
                    "roomsLeft": 0,
                    "totalWaitlistAvailable": 0,
                    "startingPrice": 7875.0,
                    "startingSolePrice": 14065.0,
                    "priceTypes": []
                },
                {
                    "elementId": 23995,
                    "name": "Platinum Twin Cabin",
                    "elementIdSole": 23996,
                    "soleOccupancyName": "Platinum Twin Cabin",
                    "serviceLevel": 1,
                    "serviceType": "Platinum Twin",
                    "occupancyId": 3,
                    "roomsLeft": 0,
                    "totalWaitlistAvailable": 0,
                    "startingPrice": 7875.0,
                    "startingSolePrice": 14065.0,
                    "priceTypes": []
                }
            ],
            "offTrainExcursions": null,
            "status": ""
        },
        {
            "departureId": 142584,
            "startDate": "2024-05-17T10:00:00",
            "startRegion": "Darwin",
            "endDate": "2024-05-21T10:50:00",
            "endRegion": "Adelaide",
            "hasCabinPriceTypes": true,
            "bookingKey": "The Ghan Expedition Darwin to Adelaide with Charles Darwin Sunset Dinner Cruise 17 May 2024",
            "cabins": [
                {
                    "elementId": 23985,
                    "name": "Gold Single Cabin",
                    "elementIdSole": 23985,
                    "soleOccupancyName": "Gold Single Cabin",
                    "serviceLevel": 3,
                    "serviceType": "Gold Single",
                    "occupancyId": 1,
                    "roomsLeft": 8,
                    "totalWaitlistAvailable": 0,
                    "startingPrice": 4320.0,
                    "startingSolePrice": 4320.0,
                    "priceTypes": [
                        {
                            "priceTypeId": 16,
                            "priceTypeName": "Saver",
                            "adultPrice": 4320.0,
                            "soleAdultPrice": 4320.0,
                            "childPrice": 0,
                            "isConcessionFare": false,
                            "terms": "This fare is a discounted fare and is subject to availability. 25% cancellation fees apply when cancelling more than 45 days prior to departure. 100% cancellation fees apply 45 days and under prior to departure.",
                            "isClassicReward": false,
                            "burnRate": 0.0055600000,
                            "earnRate": 1.0000000000,
                            "isWaitListPriceType": false
                        },
                        {
                            "priceTypeId": 2,
                            "priceTypeName": "Everyday",
                            "adultPrice": 4545.0,
                            "soleAdultPrice": 4545.0,
                            "childPrice": 0,
                            "isConcessionFare": false,
                            "terms": "A 25% deposit is due upon booking. Final payment is due 45 days prior to departure. Cancelling more than 45 days prior to departure will result a loss in deposit. 100% cancellation fees apply if cancelled 45 days or less than departure.",
                            "isClassicReward": false,
                            "burnRate": 0.0055600000,
                            "earnRate": 1.0000000000,
                            "isWaitListPriceType": false
                        },
                        {
                            "priceTypeId": 610,
                            "priceTypeName": "Flexible",
                            "adultPrice": 4985.0,
                            "soleAdultPrice": 4985.0,
                            "childPrice": 0,
                            "isConcessionFare": false,
                            "terms": "Changes are permitted up to 1 day prior to departure. Fully refundable up until 1 day prior to departure.",
                            "isClassicReward": false,
                            "burnRate": 0.0055600000,
                            "earnRate": 1.0000000000,
                            "isWaitListPriceType": false
                        }
                    ]
                },
                {
                    "elementId": 23987,
                    "name": "Gold Suite Cabin",
                    "elementIdSole": 23988,
                    "soleOccupancyName": "Gold Suite Cabin",
                    "serviceLevel": 2,
                    "serviceType": "Gold Suite",
                    "occupancyId": 3,
                    "roomsLeft": 0,
                    "totalWaitlistAvailable": 0,
                    "startingPrice": 6980.0,
                    "startingSolePrice": 12455.0,
                    "priceTypes": []
                },
                {
                    "elementId": 23989,
                    "name": "Gold Twin Cabin",
                    "elementIdSole": 23990,
                    "soleOccupancyName": "Gold Twin Cabin",
                    "serviceLevel": 2,
                    "serviceType": "Gold Twin",
                    "occupancyId": 3,
                    "roomsLeft": 0,
                    "totalWaitlistAvailable": 3,
                    "startingPrice": 4650.0,
                    "startingSolePrice": 8260.0,
                    "priceTypes": []
                },
                {
                    "elementId": 23993,
                    "name": "Platinum Double Cabin",
                    "elementIdSole": 23994,
                    "soleOccupancyName": "Platinum Double Cabin",
                    "serviceLevel": 1,
                    "serviceType": "Platinum Double",
                    "occupancyId": 3,
                    "roomsLeft": 0,
                    "totalWaitlistAvailable": 0,
                    "startingPrice": 7875.0,
                    "startingSolePrice": 14065.0,
                    "priceTypes": []
                },
                {
                    "elementId": 23995,
                    "name": "Platinum Twin Cabin",
                    "elementIdSole": 23996,
                    "soleOccupancyName": "Platinum Twin Cabin",
                    "serviceLevel": 1,
                    "serviceType": "Platinum Twin",
                    "occupancyId": 3,
                    "roomsLeft": 0,
                    "totalWaitlistAvailable": 1,
                    "startingPrice": 7875.0,
                    "startingSolePrice": 14065.0,
                    "priceTypes": []
                }
            ],
            "offTrainExcursions": null,
            "status": ""
        },
        {
            "departureId": 142554,
            "startDate": "2024-05-21T09:00:00",
            "startRegion": "Darwin",
            "endDate": "2024-05-25T11:50:00",
            "endRegion": "Adelaide",
            "hasCabinPriceTypes": true,
            "bookingKey": "The Ghan Expedition Darwin to Adelaide with Charles Darwin Sunset Dinner Cruise 21 May 2024",
            "cabins": [
                {
                    "elementId": 27631,
                    "name": "Gold Premium Suite Cabin",
                    "elementIdSole": 27632,
                    "soleOccupancyName": "Gold Premium Suite Cabin",
                    "serviceLevel": 6,
                    "serviceType": "Gold Premium Suite",
                    "occupancyId": 3,
                    "roomsLeft": 0,
                    "totalWaitlistAvailable": 0,
                    "startingPrice": 7670.0,
                    "startingSolePrice": 13700.0,
                    "priceTypes": []
                },
                {
                    "elementId": 23997,
                    "name": "Gold Premium Twin Cabin",
                    "elementIdSole": 23998,
                    "soleOccupancyName": "Gold Premium Twin Cabin",
                    "serviceLevel": 6,
                    "serviceType": "Gold Premium Twin",
                    "occupancyId": 3,
                    "roomsLeft": 2,
                    "totalWaitlistAvailable": 0,
                    "startingPrice": 5865.0,
                    "startingSolePrice": 10420.0,
                    "priceTypes": [
                        {
                            "priceTypeId": 16,
                            "priceTypeName": "Saver",
                            "adultPrice": 5865.0,
                            "soleAdultPrice": 10420.0,
                            "childPrice": 4692.0,
                            "isConcessionFare": false,
                            "terms": "This fare is a discounted fare and is subject to availability. 25% cancellation fees apply when cancelling more than 45 days prior to departure. 100% cancellation fees apply 45 days and under prior to departure.",
                            "isClassicReward": false,
                            "burnRate": 0.0055600000,
                            "earnRate": 1.0000000000,
                            "isWaitListPriceType": false
                        },
                        {
                            "priceTypeId": 2,
                            "priceTypeName": "Everyday",
                            "adultPrice": 6170.0,
                            "soleAdultPrice": 10970.0,
                            "childPrice": 4936.0,
                            "isConcessionFare": false,
                            "terms": "A 25% deposit is due upon booking. Final payment is due 45 days prior to departure. Cancelling more than 45 days prior to departure will result a loss in deposit. 100% cancellation fees apply if cancelled 45 days or less than departure.",
                            "isClassicReward": false,
                            "burnRate": 0.0055600000,
                            "earnRate": 1.0000000000,
                            "isWaitListPriceType": false
                        },
                        {
                            "priceTypeId": 610,
                            "priceTypeName": "Flexible",
                            "adultPrice": 6750.0,
                            "soleAdultPrice": 12050.0,
                            "childPrice": 5400.0,
                            "isConcessionFare": false,
                            "terms": "Changes are permitted up to 1 day prior to departure. Fully refundable up until 1 day prior to departure.",
                            "isClassicReward": false,
                            "burnRate": 0.0055600000,
                            "earnRate": 1.0000000000,
                            "isWaitListPriceType": false
                        }
                    ]
                },
                {
                    "elementId": 23985,
                    "name": "Gold Single Cabin",
                    "elementIdSole": 23985,
                    "soleOccupancyName": "Gold Single Cabin",
                    "serviceLevel": 3,
                    "serviceType": "Gold Single",
                    "occupancyId": 1,
                    "roomsLeft": 22,
                    "totalWaitlistAvailable": 0,
                    "startingPrice": 4320.0,
                    "startingSolePrice": 4320.0,
                    "priceTypes": [
                        {
                            "priceTypeId": 16,
                            "priceTypeName": "Saver",
                            "adultPrice": 4320.0,
                            "soleAdultPrice": 4320.0,
                            "childPrice": 0,
                            "isConcessionFare": false,
                            "terms": "This fare is a discounted fare and is subject to availability. 25% cancellation fees apply when cancelling more than 45 days prior to departure. 100% cancellation fees apply 45 days and under prior to departure.",
                            "isClassicReward": false,
                            "burnRate": 0.0055600000,
                            "earnRate": 1.0000000000,
                            "isWaitListPriceType": false
                        },
                        {
                            "priceTypeId": 2,
                            "priceTypeName": "Everyday",
                            "adultPrice": 4545.0,
                            "soleAdultPrice": 4545.0,
                            "childPrice": 0,
                            "isConcessionFare": false,
                            "terms": "A 25% deposit is due upon booking. Final payment is due 45 days prior to departure. Cancelling more than 45 days prior to departure will result a loss in deposit. 100% cancellation fees apply if cancelled 45 days or less than departure.",
                            "isClassicReward": false,
                            "burnRate": 0.0055600000,
                            "earnRate": 1.0000000000,
                            "isWaitListPriceType": false
                        },
                        {
                            "priceTypeId": 610,
                            "priceTypeName": "Flexible",
                            "adultPrice": 4985.0,
                            "soleAdultPrice": 4985.0,
                            "childPrice": 0,
                            "isConcessionFare": false,
                            "terms": "Changes are permitted up to 1 day prior to departure. Fully refundable up until 1 day prior to departure.",
                            "isClassicReward": false,
                            "burnRate": 0.0055600000,
                            "earnRate": 1.0000000000,
                            "isWaitListPriceType": false
                        }
                    ]
                },
                {
                    "elementId": 23987,
                    "name": "Gold Suite Cabin",
                    "elementIdSole": 23988,
                    "soleOccupancyName": "Gold Suite Cabin",
                    "serviceLevel": 2,
                    "serviceType": "Gold Suite",
                    "occupancyId": 3,
                    "roomsLeft": 0,
                    "totalWaitlistAvailable": 1,
                    "startingPrice": 6980.0,
                    "startingSolePrice": 12455.0,
                    "priceTypes": []
                },
                {
                    "elementId": 23989,
                    "name": "Gold Twin Cabin",
                    "elementIdSole": 23990,
                    "soleOccupancyName": "Gold Twin Cabin",
                    "serviceLevel": 2,
                    "serviceType": "Gold Twin",
                    "occupancyId": 3,
                    "roomsLeft": 1,
                    "totalWaitlistAvailable": 0,
                    "startingPrice": 4900.0,
                    "startingSolePrice": 8710.0,
                    "priceTypes": [
                        {
                            "priceTypeId": 16,
                            "priceTypeName": "Saver",
                            "adultPrice": 4900.0,
                            "soleAdultPrice": 8710.0,
                            "childPrice": 3920.0,
                            "isConcessionFare": false,
                            "terms": "This fare is a discounted fare and is subject to availability. 25% cancellation fees apply when cancelling more than 45 days prior to departure. 100% cancellation fees apply 45 days and under prior to departure.",
                            "isClassicReward": false,
                            "burnRate": 0.0055600000,
                            "earnRate": 1.0000000000,
                            "isWaitListPriceType": false
                        },
                        {
                            "priceTypeId": 2,
                            "priceTypeName": "Everyday",
                            "adultPrice": 5155.0,
                            "soleAdultPrice": 9170.0,
                            "childPrice": 4124.0,
                            "isConcessionFare": false,
                            "terms": "A 25% deposit is due upon booking. Final payment is due 45 days prior to departure. Cancelling more than 45 days prior to departure will result a loss in deposit. 100% cancellation fees apply if cancelled 45 days or less than departure.",
                            "isClassicReward": false,
                            "burnRate": 0.0055600000,
                            "earnRate": 1.0000000000,
                            "isWaitListPriceType": false
                        },
                        {
                            "priceTypeId": 610,
                            "priceTypeName": "Flexible",
                            "adultPrice": 5655.0,
                            "soleAdultPrice": 10070.0,
                            "childPrice": 4524.0,
                            "isConcessionFare": false,
                            "terms": "Changes are permitted up to 1 day prior to departure. Fully refundable up until 1 day prior to departure.",
                            "isClassicReward": false,
                            "burnRate": 0.0055600000,
                            "earnRate": 1.0000000000,
                            "isWaitListPriceType": false
                        }
                    ]
                },
                {
                    "elementId": 23993,
                    "name": "Platinum Double Cabin",
                    "elementIdSole": 23994,
                    "soleOccupancyName": "Platinum Double Cabin",
                    "serviceLevel": 1,
                    "serviceType": "Platinum Double",
                    "occupancyId": 3,
                    "roomsLeft": 0,
                    "totalWaitlistAvailable": 1,
                    "startingPrice": 7875.0,
                    "startingSolePrice": 14065.0,
                    "priceTypes": []
                },
                {
                    "elementId": 23995,
                    "name": "Platinum Twin Cabin",
                    "elementIdSole": 23996,
                    "soleOccupancyName": "Platinum Twin Cabin",
                    "serviceLevel": 1,
                    "serviceType": "Platinum Twin",
                    "occupancyId": 3,
                    "roomsLeft": 0,
                    "totalWaitlistAvailable": 0,
                    "startingPrice": 7875.0,
                    "startingSolePrice": 14065.0,
                    "priceTypes": []
                }
            ],
            "offTrainExcursions": null,
            "status": ""
        },
        {
            "departureId": 142585,
            "startDate": "2024-05-24T10:00:00",
            "startRegion": "Darwin",
            "endDate": "2024-05-28T10:50:00",
            "endRegion": "Adelaide",
            "hasCabinPriceTypes": true,
            "bookingKey": "The Ghan Expedition Darwin to Adelaide with Charles Darwin Sunset Dinner Cruise 24 May 2024",
            "cabins": [
                {
                    "elementId": 23985,
                    "name": "Gold Single Cabin",
                    "elementIdSole": 23985,
                    "soleOccupancyName": "Gold Single Cabin",
                    "serviceLevel": 3,
                    "serviceType": "Gold Single",
                    "occupancyId": 1,
                    "roomsLeft": 8,
                    "totalWaitlistAvailable": 0,
                    "startingPrice": 4320.0,
                    "startingSolePrice": 4320.0,
                    "priceTypes": [
                        {
                            "priceTypeId": 16,
                            "priceTypeName": "Saver",
                            "adultPrice": 4320.0,
                            "soleAdultPrice": 4320.0,
                            "childPrice": 0,
                            "isConcessionFare": false,
                            "terms": "This fare is a discounted fare and is subject to availability. 25% cancellation fees apply when cancelling more than 45 days prior to departure. 100% cancellation fees apply 45 days and under prior to departure.",
                            "isClassicReward": false,
                            "burnRate": 0.0055600000,
                            "earnRate": 1.0000000000,
                            "isWaitListPriceType": false
                        },
                        {
                            "priceTypeId": 2,
                            "priceTypeName": "Everyday",
                            "adultPrice": 4545.0,
                            "soleAdultPrice": 4545.0,
                            "childPrice": 0,
                            "isConcessionFare": false,
                            "terms": "A 25% deposit is due upon booking. Final payment is due 45 days prior to departure. Cancelling more than 45 days prior to departure will result a loss in deposit. 100% cancellation fees apply if cancelled 45 days or less than departure.",
                            "isClassicReward": false,
                            "burnRate": 0.0055600000,
                            "earnRate": 1.0000000000,
                            "isWaitListPriceType": false
                        },
                        {
                            "priceTypeId": 610,
                            "priceTypeName": "Flexible",
                            "adultPrice": 4985.0,
                            "soleAdultPrice": 4985.0,
                            "childPrice": 0,
                            "isConcessionFare": false,
                            "terms": "Changes are permitted up to 1 day prior to departure. Fully refundable up until 1 day prior to departure.",
                            "isClassicReward": false,
                            "burnRate": 0.0055600000,
                            "earnRate": 1.0000000000,
                            "isWaitListPriceType": false
                        }
                    ]
                },
                {
                    "elementId": 23987,
                    "name": "Gold Suite Cabin",
                    "elementIdSole": 23988,
                    "soleOccupancyName": "Gold Suite Cabin",
                    "serviceLevel": 2,
                    "serviceType": "Gold Suite",
                    "occupancyId": 3,
                    "roomsLeft": 0,
                    "totalWaitlistAvailable": 0,
                    "startingPrice": 6980.0,
                    "startingSolePrice": 12455.0,
                    "priceTypes": []
                },
                {
                    "elementId": 23989,
                    "name": "Gold Twin Cabin",
                    "elementIdSole": 23990,
                    "soleOccupancyName": "Gold Twin Cabin",
                    "serviceLevel": 2,
                    "serviceType": "Gold Twin",
                    "occupancyId": 3,
                    "roomsLeft": 14,
                    "totalWaitlistAvailable": 0,
                    "startingPrice": 4900.0,
                    "startingSolePrice": 8710.0,
                    "priceTypes": [
                        {
                            "priceTypeId": 16,
                            "priceTypeName": "Saver",
                            "adultPrice": 4900.0,
                            "soleAdultPrice": 8710.0,
                            "childPrice": 3920.0,
                            "isConcessionFare": false,
                            "terms": "This fare is a discounted fare and is subject to availability. 25% cancellation fees apply when cancelling more than 45 days prior to departure. 100% cancellation fees apply 45 days and under prior to departure.",
                            "isClassicReward": false,
                            "burnRate": 0.0055600000,
                            "earnRate": 1.0000000000,
                            "isWaitListPriceType": false
                        },
                        {
                            "priceTypeId": 2,
                            "priceTypeName": "Everyday",
                            "adultPrice": 5155.0,
                            "soleAdultPrice": 9170.0,
                            "childPrice": 4124.0,
                            "isConcessionFare": false,
                            "terms": "A 25% deposit is due upon booking. Final payment is due 45 days prior to departure. Cancelling more than 45 days prior to departure will result a loss in deposit. 100% cancellation fees apply if cancelled 45 days or less than departure.",
                            "isClassicReward": false,
                            "burnRate": 0.0055600000,
                            "earnRate": 1.0000000000,
                            "isWaitListPriceType": false
                        },
                        {
                            "priceTypeId": 610,
                            "priceTypeName": "Flexible",
                            "adultPrice": 5655.0,
                            "soleAdultPrice": 10070.0,
                            "childPrice": 4524.0,
                            "isConcessionFare": false,
                            "terms": "Changes are permitted up to 1 day prior to departure. Fully refundable up until 1 day prior to departure.",
                            "isClassicReward": false,
                            "burnRate": 0.0055600000,
                            "earnRate": 1.0000000000,
                            "isWaitListPriceType": false
                        }
                    ]
                },
                {
                    "elementId": 23993,
                    "name": "Platinum Double Cabin",
                    "elementIdSole": 23994,
                    "soleOccupancyName": "Platinum Double Cabin",
                    "serviceLevel": 1,
                    "serviceType": "Platinum Double",
                    "occupancyId": 3,
                    "roomsLeft": 1,
                    "totalWaitlistAvailable": 0,
                    "startingPrice": 7875.0,
                    "startingSolePrice": 14065.0,
                    "priceTypes": [
                        {
                            "priceTypeId": 2,
                            "priceTypeName": "Everyday",
                            "adultPrice": 7875.0,
                            "soleAdultPrice": 14065.0,
                            "childPrice": 7875.0,
                            "isConcessionFare": false,
                            "terms": "A 25% deposit is due upon booking. Final payment is due 45 days prior to departure. Cancelling more than 45 days prior to departure will result a loss in deposit. 100% cancellation fees apply if cancelled 45 days or less than departure.",
                            "isClassicReward": false,
                            "burnRate": 0.0055600000,
                            "earnRate": 1.0000000000,
                            "isWaitListPriceType": false
                        },
                        {
                            "priceTypeId": 610,
                            "priceTypeName": "Flexible",
                            "adultPrice": 8650.0,
                            "soleAdultPrice": 15460.0,
                            "childPrice": 8650.0,
                            "isConcessionFare": false,
                            "terms": "Changes are permitted up to 1 day prior to departure. Fully refundable up until 1 day prior to departure.",
                            "isClassicReward": false,
                            "burnRate": 0.0055600000,
                            "earnRate": 1.0000000000,
                            "isWaitListPriceType": false
                        }
                    ]
                },
                {
                    "elementId": 23995,
                    "name": "Platinum Twin Cabin",
                    "elementIdSole": 23996,
                    "soleOccupancyName": "Platinum Twin Cabin",
                    "serviceLevel": 1,
                    "serviceType": "Platinum Twin",
                    "occupancyId": 3,
                    "roomsLeft": 0,
                    "totalWaitlistAvailable": 0,
                    "startingPrice": 7875.0,
                    "startingSolePrice": 14065.0,
                    "priceTypes": []
                }
            ],
            "offTrainExcursions": null,
            "status": ""
        },
        {
            "departureId": 142555,
            "startDate": "2024-05-28T09:00:00",
            "startRegion": "Darwin",
            "endDate": "2024-06-01T11:50:00",
            "endRegion": "Adelaide",
            "hasCabinPriceTypes": true,
            "bookingKey": "The Ghan Expedition Darwin to Adelaide with Charles Darwin Sunset Dinner Cruise 28 May 2024",
            "cabins": [
                {
                    "elementId": 27631,
                    "name": "Gold Premium Suite Cabin",
                    "elementIdSole": 27632,
                    "soleOccupancyName": "Gold Premium Suite Cabin",
                    "serviceLevel": 6,
                    "serviceType": "Gold Premium Suite",
                    "occupancyId": 3,
                    "roomsLeft": 0,
                    "totalWaitlistAvailable": 1,
                    "startingPrice": 7670.0,
                    "startingSolePrice": 13700.0,
                    "priceTypes": []
                },
                {
                    "elementId": 23997,
                    "name": "Gold Premium Twin Cabin",
                    "elementIdSole": 23998,
                    "soleOccupancyName": "Gold Premium Twin Cabin",
                    "serviceLevel": 6,
                    "serviceType": "Gold Premium Twin",
                    "occupancyId": 3,
                    "roomsLeft": 3,
                    "totalWaitlistAvailable": 0,
                    "startingPrice": 5865.0,
                    "startingSolePrice": 10420.0,
                    "priceTypes": [
                        {
                            "priceTypeId": 16,
                            "priceTypeName": "Saver",
                            "adultPrice": 5865.0,
                            "soleAdultPrice": 10420.0,
                            "childPrice": 4692.0,
                            "isConcessionFare": false,
                            "terms": "This fare is a discounted fare and is subject to availability. 25% cancellation fees apply when cancelling more than 45 days prior to departure. 100% cancellation fees apply 45 days and under prior to departure.",
                            "isClassicReward": false,
                            "burnRate": 0.0055600000,
                            "earnRate": 1.0000000000,
                            "isWaitListPriceType": false
                        },
                        {
                            "priceTypeId": 2,
                            "priceTypeName": "Everyday",
                            "adultPrice": 6170.0,
                            "soleAdultPrice": 10970.0,
                            "childPrice": 4936.0,
                            "isConcessionFare": false,
                            "terms": "A 25% deposit is due upon booking. Final payment is due 45 days prior to departure. Cancelling more than 45 days prior to departure will result a loss in deposit. 100% cancellation fees apply if cancelled 45 days or less than departure.",
                            "isClassicReward": false,
                            "burnRate": 0.0055600000,
                            "earnRate": 1.0000000000,
                            "isWaitListPriceType": false
                        },
                        {
                            "priceTypeId": 610,
                            "priceTypeName": "Flexible",
                            "adultPrice": 6750.0,
                            "soleAdultPrice": 12050.0,
                            "childPrice": 5400.0,
                            "isConcessionFare": false,
                            "terms": "Changes are permitted up to 1 day prior to departure. Fully refundable up until 1 day prior to departure.",
                            "isClassicReward": false,
                            "burnRate": 0.0055600000,
                            "earnRate": 1.0000000000,
                            "isWaitListPriceType": false
                        }
                    ]
                },
                {
                    "elementId": 23985,
                    "name": "Gold Single Cabin",
                    "elementIdSole": 23985,
                    "soleOccupancyName": "Gold Single Cabin",
                    "serviceLevel": 3,
                    "serviceType": "Gold Single",
                    "occupancyId": 1,
                    "roomsLeft": 16,
                    "totalWaitlistAvailable": 0,
                    "startingPrice": 4320.0,
                    "startingSolePrice": 4320.0,
                    "priceTypes": [
                        {
                            "priceTypeId": 16,
                            "priceTypeName": "Saver",
                            "adultPrice": 4320.0,
                            "soleAdultPrice": 4320.0,
                            "childPrice": 0,
                            "isConcessionFare": false,
                            "terms": "This fare is a discounted fare and is subject to availability. 25% cancellation fees apply when cancelling more than 45 days prior to departure. 100% cancellation fees apply 45 days and under prior to departure.",
                            "isClassicReward": false,
                            "burnRate": 0.0055600000,
                            "earnRate": 1.0000000000,
                            "isWaitListPriceType": false
                        },
                        {
                            "priceTypeId": 2,
                            "priceTypeName": "Everyday",
                            "adultPrice": 4545.0,
                            "soleAdultPrice": 4545.0,
                            "childPrice": 0,
                            "isConcessionFare": false,
                            "terms": "A 25% deposit is due upon booking. Final payment is due 45 days prior to departure. Cancelling more than 45 days prior to departure will result a loss in deposit. 100% cancellation fees apply if cancelled 45 days or less than departure.",
                            "isClassicReward": false,
                            "burnRate": 0.0055600000,
                            "earnRate": 1.0000000000,
                            "isWaitListPriceType": false
                        },
                        {
                            "priceTypeId": 610,
                            "priceTypeName": "Flexible",
                            "adultPrice": 4985.0,
                            "soleAdultPrice": 4985.0,
                            "childPrice": 0,
                            "isConcessionFare": false,
                            "terms": "Changes are permitted up to 1 day prior to departure. Fully refundable up until 1 day prior to departure.",
                            "isClassicReward": false,
                            "burnRate": 0.0055600000,
                            "earnRate": 1.0000000000,
                            "isWaitListPriceType": false
                        }
                    ]
                },
                {
                    "elementId": 23987,
                    "name": "Gold Suite Cabin",
                    "elementIdSole": 23988,
                    "soleOccupancyName": "Gold Suite Cabin",
                    "serviceLevel": 2,
                    "serviceType": "Gold Suite",
                    "occupancyId": 3,
                    "roomsLeft": 0,
                    "totalWaitlistAvailable": 0,
                    "startingPrice": 6980.0,
                    "startingSolePrice": 12455.0,
                    "priceTypes": []
                },
                {
                    "elementId": 23989,
                    "name": "Gold Twin Cabin",
                    "elementIdSole": 23990,
                    "soleOccupancyName": "Gold Twin Cabin",
                    "serviceLevel": 2,
                    "serviceType": "Gold Twin",
                    "occupancyId": 3,
                    "roomsLeft": 0,
                    "totalWaitlistAvailable": 1,
                    "startingPrice": 4650.0,
                    "startingSolePrice": 8260.0,
                    "priceTypes": []
                },
                {
                    "elementId": 23993,
                    "name": "Platinum Double Cabin",
                    "elementIdSole": 23994,
                    "soleOccupancyName": "Platinum Double Cabin",
                    "serviceLevel": 1,
                    "serviceType": "Platinum Double",
                    "occupancyId": 3,
                    "roomsLeft": 0,
                    "totalWaitlistAvailable": 0,
                    "startingPrice": 7875.0,
                    "startingSolePrice": 14065.0,
                    "priceTypes": []
                },
                {
                    "elementId": 23995,
                    "name": "Platinum Twin Cabin",
                    "elementIdSole": 23996,
                    "soleOccupancyName": "Platinum Twin Cabin",
                    "serviceLevel": 1,
                    "serviceType": "Platinum Twin",
                    "occupancyId": 3,
                    "roomsLeft": 0,
                    "totalWaitlistAvailable": 1,
                    "startingPrice": 7875.0,
                    "startingSolePrice": 14065.0,
                    "priceTypes": []
                }
            ],
            "offTrainExcursions": null,
            "status": ""
        },
        {
            "departureId": 142586,
            "startDate": "2024-05-31T10:00:00",
            "startRegion": "Darwin",
            "endDate": "2024-06-04T10:50:00",
            "endRegion": "Adelaide",
            "hasCabinPriceTypes": true,
            "bookingKey": "The Ghan Expedition Darwin to Adelaide with Charles Darwin Sunset Dinner Cruise 31 May 2024",
            "cabins": [
                {
                    "elementId": 23985,
                    "name": "Gold Single Cabin",
                    "elementIdSole": 23985,
                    "soleOccupancyName": "Gold Single Cabin",
                    "serviceLevel": 3,
                    "serviceType": "Gold Single",
                    "occupancyId": 1,
                    "roomsLeft": 14,
                    "totalWaitlistAvailable": 0,
                    "startingPrice": 4320.0,
                    "startingSolePrice": 4320.0,
                    "priceTypes": [
                        {
                            "priceTypeId": 16,
                            "priceTypeName": "Saver",
                            "adultPrice": 4320.0,
                            "soleAdultPrice": 4320.0,
                            "childPrice": 0,
                            "isConcessionFare": false,
                            "terms": "This fare is a discounted fare and is subject to availability. 25% cancellation fees apply when cancelling more than 45 days prior to departure. 100% cancellation fees apply 45 days and under prior to departure.",
                            "isClassicReward": false,
                            "burnRate": 0.0055600000,
                            "earnRate": 1.0000000000,
                            "isWaitListPriceType": false
                        },
                        {
                            "priceTypeId": 2,
                            "priceTypeName": "Everyday",
                            "adultPrice": 4545.0,
                            "soleAdultPrice": 4545.0,
                            "childPrice": 0,
                            "isConcessionFare": false,
                            "terms": "A 25% deposit is due upon booking. Final payment is due 45 days prior to departure. Cancelling more than 45 days prior to departure will result a loss in deposit. 100% cancellation fees apply if cancelled 45 days or less than departure.",
                            "isClassicReward": false,
                            "burnRate": 0.0055600000,
                            "earnRate": 1.0000000000,
                            "isWaitListPriceType": false
                        },
                        {
                            "priceTypeId": 610,
                            "priceTypeName": "Flexible",
                            "adultPrice": 4985.0,
                            "soleAdultPrice": 4985.0,
                            "childPrice": 0,
                            "isConcessionFare": false,
                            "terms": "Changes are permitted up to 1 day prior to departure. Fully refundable up until 1 day prior to departure.",
                            "isClassicReward": false,
                            "burnRate": 0.0055600000,
                            "earnRate": 1.0000000000,
                            "isWaitListPriceType": false
                        }
                    ]
                },
                {
                    "elementId": 23987,
                    "name": "Gold Suite Cabin",
                    "elementIdSole": 23988,
                    "soleOccupancyName": "Gold Suite Cabin",
                    "serviceLevel": 2,
                    "serviceType": "Gold Suite",
                    "occupancyId": 3,
                    "roomsLeft": 0,
                    "totalWaitlistAvailable": 0,
                    "startingPrice": 6980.0,
                    "startingSolePrice": 12455.0,
                    "priceTypes": []
                },
                {
                    "elementId": 23989,
                    "name": "Gold Twin Cabin",
                    "elementIdSole": 23990,
                    "soleOccupancyName": "Gold Twin Cabin",
                    "serviceLevel": 2,
                    "serviceType": "Gold Twin",
                    "occupancyId": 3,
                    "roomsLeft": 8,
                    "totalWaitlistAvailable": 0,
                    "startingPrice": 4900.0,
                    "startingSolePrice": 8710.0,
                    "priceTypes": [
                        {
                            "priceTypeId": 16,
                            "priceTypeName": "Saver",
                            "adultPrice": 4900.0,
                            "soleAdultPrice": 8710.0,
                            "childPrice": 3920.0,
                            "isConcessionFare": false,
                            "terms": "This fare is a discounted fare and is subject to availability. 25% cancellation fees apply when cancelling more than 45 days prior to departure. 100% cancellation fees apply 45 days and under prior to departure.",
                            "isClassicReward": false,
                            "burnRate": 0.0055600000,
                            "earnRate": 1.0000000000,
                            "isWaitListPriceType": false
                        },
                        {
                            "priceTypeId": 2,
                            "priceTypeName": "Everyday",
                            "adultPrice": 5155.0,
                            "soleAdultPrice": 9170.0,
                            "childPrice": 4124.0,
                            "isConcessionFare": false,
                            "terms": "A 25% deposit is due upon booking. Final payment is due 45 days prior to departure. Cancelling more than 45 days prior to departure will result a loss in deposit. 100% cancellation fees apply if cancelled 45 days or less than departure.",
                            "isClassicReward": false,
                            "burnRate": 0.0055600000,
                            "earnRate": 1.0000000000,
                            "isWaitListPriceType": false
                        },
                        {
                            "priceTypeId": 610,
                            "priceTypeName": "Flexible",
                            "adultPrice": 5655.0,
                            "soleAdultPrice": 10070.0,
                            "childPrice": 4524.0,
                            "isConcessionFare": false,
                            "terms": "Changes are permitted up to 1 day prior to departure. Fully refundable up until 1 day prior to departure.",
                            "isClassicReward": false,
                            "burnRate": 0.0055600000,
                            "earnRate": 1.0000000000,
                            "isWaitListPriceType": false
                        }
                    ]
                },
                {
                    "elementId": 23993,
                    "name": "Platinum Double Cabin",
                    "elementIdSole": 23994,
                    "soleOccupancyName": "Platinum Double Cabin",
                    "serviceLevel": 1,
                    "serviceType": "Platinum Double",
                    "occupancyId": 3,
                    "roomsLeft": 1,
                    "totalWaitlistAvailable": 0,
                    "startingPrice": 7875.0,
                    "startingSolePrice": 14065.0,
                    "priceTypes": [
                        {
                            "priceTypeId": 2,
                            "priceTypeName": "Everyday",
                            "adultPrice": 7875.0,
                            "soleAdultPrice": 14065.0,
                            "childPrice": 7875.0,
                            "isConcessionFare": false,
                            "terms": "A 25% deposit is due upon booking. Final payment is due 45 days prior to departure. Cancelling more than 45 days prior to departure will result a loss in deposit. 100% cancellation fees apply if cancelled 45 days or less than departure.",
                            "isClassicReward": false,
                            "burnRate": 0.0055600000,
                            "earnRate": 1.0000000000,
                            "isWaitListPriceType": false
                        },
                        {
                            "priceTypeId": 610,
                            "priceTypeName": "Flexible",
                            "adultPrice": 8650.0,
                            "soleAdultPrice": 15460.0,
                            "childPrice": 8650.0,
                            "isConcessionFare": false,
                            "terms": "Changes are permitted up to 1 day prior to departure. Fully refundable up until 1 day prior to departure.",
                            "isClassicReward": false,
                            "burnRate": 0.0055600000,
                            "earnRate": 1.0000000000,
                            "isWaitListPriceType": false
                        }
                    ]
                },
                {
                    "elementId": 23995,
                    "name": "Platinum Twin Cabin",
                    "elementIdSole": 23996,
                    "soleOccupancyName": "Platinum Twin Cabin",
                    "serviceLevel": 1,
                    "serviceType": "Platinum Twin",
                    "occupancyId": 3,
                    "roomsLeft": 0,
                    "totalWaitlistAvailable": 0,
                    "startingPrice": 7875.0,
                    "startingSolePrice": 14065.0,
                    "priceTypes": []
                }
            ],
            "offTrainExcursions": null,
            "status": ""
        }
    ],
    "recommendedPackages": null
}